aa_airtable/__init__.py
aa_airtable/admin.py
aa_airtable/celery.py
aa_airtable/download.py
aa_airtable/models.py
aa_airtable/parser.py
aa_airtable/settings.py
aa_airtable/tasks.py
aa_airtable/__pycache__/__init__.cpython-36.pyc
aa_airtable/__pycache__/admin.cpython-36.pyc
aa_airtable/__pycache__/celery.cpython-36.pyc
aa_airtable/__pycache__/download.cpython-36.pyc
aa_airtable/__pycache__/models.cpython-36.pyc
aa_airtable/__pycache__/settings.cpython-36.pyc
aa_airtable/__pycache__/tasks.cpython-36.pyc
aa_airtable/migrations/0001_initial.py
aa_airtable/migrations/__init__.py
aa_airtable/migrations/__pycache__/__init__.cpython-36.pyc
aa_airtable-0.2.dist-info/DESCRIPTION.rst
aa_airtable-0.2.dist-info/METADATA
aa_airtable-0.2.dist-info/RECORD
aa_airtable-0.2.dist-info/WHEEL
aa_airtable-0.2.dist-info/metadata.json
aa_airtable-0.2.dist-info/top_level.txt
