Metadata-Version: 2.0
Name: aa-airtable
Version: 0.2
Summary: Airtable integration for Django-based projects
Home-page: https://github.com/ArabellaTech/aa-airtable
Author: Remigiusz Dymecki
Author-email: remi@arabel.la
License: MIT
Platform: UNKNOWN
Classifier: Development Status :: 3 - Alpha
Classifier: Environment :: Web Environment
Classifier: Framework :: Django
Classifier: Intended Audience :: Developers
Classifier: Operating System :: OS Independent
Classifier: Programming Language :: Python
Classifier: Programming Language :: Python :: 2.7
Classifier: Programming Language :: Python :: 3.4
Classifier: Programming Language :: Python :: 3.5
Classifier: Programming Language :: Python :: 3.6
Classifier: Topic :: Internet :: WWW/HTTP
Requires-Dist: celery (>=3.1.0)
Requires-Dist: requests (>=2.0.0)
